cs.ratelimit-1.3.1-py3.11-nspkg.pth
cs/ratelimit/__init__.py
cs/ratelimit/components.py
cs/ratelimit/configure.zcml
cs/ratelimit/decorators.py
cs/ratelimit/exceptions.py
cs/ratelimit/ftesting.zcml
cs/ratelimit/interfaces.py
cs/ratelimit/testing.py
cs/ratelimit/tests/__init__.py
cs/ratelimit/tests/test_components.py
cs/ratelimit/tests/test_decorators.py
cs.ratelimit-1.3.1.data/scripts/lint.sh
cs.ratelimit-1.3.1.data/scripts/run-tests.sh
cs.ratelimit-1.3.1.dist-info/LICENSE
cs.ratelimit-1.3.1.dist-info/METADATA
cs.ratelimit-1.3.1.dist-info/WHEEL
cs.ratelimit-1.3.1.dist-info/namespace_packages.txt
cs.ratelimit-1.3.1.dist-info/top_level.txt
cs.ratelimit-1.3.1.dist-info/RECORD
