Metadata-Version: 2.1
Name: cs.ratelimit
Version: 1.3.1
Summary: Ratelimit components
Home-page: https://github.com/CrowdStrike/cs.ratelimit
Author: David Davis
Author-email: david.davis@crowdstrike.com
Maintainer: Forrest Aldridge
Maintainer-email: forrest.aldridge@crowdstrike.com
Classifier: Development Status :: 5 - Production/Stable
Classifier: Intended Audience :: Developers
Classifier: Natural Language :: English
Classifier: Operating System :: Unix
Classifier: Operating System :: POSIX
Classifier: Operating System :: POSIX :: Linux
Classifier: Operating System :: MacOS
Classifier: Operating System :: Microsoft :: Windows
Classifier: Operating System :: OS Independent
Classifier: Programming Language :: Python
Classifier: Programming Language :: Python :: 3
Classifier: Programming Language :: Python :: 3.8
Classifier: Programming Language :: Python :: 3.9
Classifier: Programming Language :: Python :: 3.10
Classifier: Programming Language :: Python :: 3.11
Classifier: Programming Language :: Python :: 3.12
Classifier: Framework :: Zope
Classifier: Framework :: Flake8
Classifier: License :: OSI Approved :: MIT License
Classifier: Topic :: Software Development :: Libraries :: Python Modules
Classifier: Topic :: Utilities
Requires-Python: >=3.8
License-File: LICENSE
Requires-Dist: setuptools
Requires-Dist: zope.component
Requires-Dist: zope.interface
Requires-Dist: zope.schema
Provides-Extra: dev
Requires-Dist: zope.testrunner ; extra == 'dev'
Requires-Dist: zope.configuration ; extra == 'dev'
Requires-Dist: bandit ; extra == 'dev'
Requires-Dist: coverage ; extra == 'dev'
Requires-Dist: flake8 ; extra == 'dev'
Requires-Dist: pydocstyle ; extra == 'dev'
Requires-Dist: pylint ; extra == 'dev'
